agents/__init__.py
agents/agente_web.py
agents/analista_ventas.py
agents/experto_estudios.py
agents/synthesizer.py
agents/text_sql.py
api/__init__.py
api/bot_framework.py
api/main.py
api/market_study_engine.py
api/sales_engine.py
api/search_engine.py
api/super_engine.py
config/__init__.py
config/params.py
config/prompts.py
core/__init__.py
core/base_agent.py
core/base_bot.py
core/base_engine.py
core/base_node.py
core/base_node_complex.py
main/__init__.py
main/market_study_bot.py
main/sales_bot.py
main/search_bot.py
main/super_bot.py
models/__init__.py
models/agentic_llm.py
models/databricks_llm.py
multi_agent_bot-1.0.0.dist-info/licenses/LICENSE
nodes/__init__.py
nodes/market_study.py
nodes/research_team.py
nodes/sales.py
nodes/search.py
nodes/supervisor.py
nodes/synthesizer.py
nodes/text_sql.py
schemas/__init__.py
schemas/api_query_request.py
schemas/state.py
schemas/vector_search_input.py
tools/__init__.py
tools/vector_search.py
tools/web_search.py
utils/__init__.py
utils/logger.py
utils/mlflow_cleanup.py
utils/session_manager.py
utils/summarizer.py
utils/tavily.py
multi_agent_bot-1.0.0.dist-info/METADATA
multi_agent_bot-1.0.0.dist-info/WHEEL
multi_agent_bot-1.0.0.dist-info/entry_points.txt
multi_agent_bot-1.0.0.dist-info/top_level.txt
multi_agent_bot-1.0.0.dist-info/RECORD
