Metadata-Version: 2.4
Name: multi-agent-bot
Version: 1.0.0
Summary: A multi-agent bot framework for research and automation
Home-page: https://github.com/jpalvarezb/multi-agent-bot
Author: jpalvarezb
Author-email: jpalvarezb <jpalvarezb@users.noreply.github.com>
License: MIT License
Project-URL: Homepage, https://github.com/jpalvarezb/multi-agent-bot
Project-URL: Bug Reports, https://github.com/jpalvarezb/multi-agent-bot/issues
Project-URL: Source, https://github.com/jpalvarezb/multi-agent-bot
Project-URL: Documentation, https://github.com/jpalvarezb/multi-agent-bot#readme
Keywords: ai,agents,langchain,langgraph,chatbots,automation
Classifier: Development Status :: 3 - Alpha
Classifier: Intended Audience :: Developers
Classifier: License :: OSI Approved :: MIT License
Classifier: Operating System :: OS Independent
Classifier: Programming Language :: Python :: 3
Classifier: Programming Language :: Python :: 3.11
Classifier: Programming Language :: Python :: 3.12
Requires-Python: >=3.11
License-File: LICENSE
Requires-Dist: fastapi==0.116.1
Requires-Dist: uvicorn==0.35.0
Requires-Dist: langchain==0.3.26
Requires-Dist: langchain-community==0.3.27
Requires-Dist: langchain-core==0.3.69
Requires-Dist: langchain-text-splitters==0.3.8
Requires-Dist: langgraph==0.5.3
Requires-Dist: langgraph-prebuilt==0.5.2
Requires-Dist: pydantic==2.11.7
Requires-Dist: python-dotenv==1.1.1
Requires-Dist: requests==2.32.4
Requires-Dist: databricks-sdk==0.59.0
Requires-Dist: databricks-ai-bridge==0.6.0
Requires-Dist: databricks-langchain==0.6.0
Requires-Dist: databricks-vectorsearch==0.57
Requires-Dist: numpy==1.26.4
Requires-Dist: pandas==2.3.1
Requires-Dist: scikit-learn==1.7.1
Requires-Dist: gunicorn==23.0.0
Requires-Dist: python-multipart==0.0.9
Requires-Dist: langchain-openai==0.3.28
Requires-Dist: langchain-tavily==0.2.10
Requires-Dist: botbuilder-core==4.14.3
Requires-Dist: botbuilder-schema==4.14.3
Requires-Dist: botframework-connector==4.14.3
Requires-Dist: aiohttp>=3.9.0
Requires-Dist: PyJWT==2.8.0
Dynamic: author
Dynamic: home-page
Dynamic: license-file
Dynamic: requires-python
